micro_components/__init__.py
micro_components/setup.py
micro_components/components/__init__.py
micro_components/components/builder.py
micro_components/tests/__init__.py
micro_components/tests/test_micro-components.py
micro_components/utils/__init__.py
micro_components/utils/formats.py
micro_components/utils/funcs.py
micro_components/utils/jsons.py
micro_components/utils/shell.py
micro_components/utils/classes/Cache.py
micro_components/utils/classes/Component.py
micro_components/utils/classes/Hookable.py
micro_components/utils/classes/JsonStore.py
micro_components/utils/classes/__init__.py
micro_components-0.1.6.dist-info/METADATA
micro_components-0.1.6.dist-info/WHEEL
micro_components-0.1.6.dist-info/top_level.txt
micro_components-0.1.6.dist-info/RECORD
